interval_repeat_decorator/LICENSE
interval_repeat_decorator/README.MD
interval_repeat_decorator/__init__.py
interval_repeat_decorator/requirements.txt
interval_repeat_decorator/thirdparty.json
interval_repeat_decorator-0.10.dist-info/LICENSE.rst
interval_repeat_decorator-0.10.dist-info/METADATA
interval_repeat_decorator-0.10.dist-info/WHEEL
interval_repeat_decorator-0.10.dist-info/top_level.txt
interval_repeat_decorator-0.10.dist-info/RECORD
